Junkyard/__init__.py
Junkyard/cyberdyne_legacy.py
Junkyard/garbagebasket_legacy.py
Junkyard-0.0.3a5.dist-info/LICENSE
Junkyard-0.0.3a5.dist-info/METADATA
Junkyard-0.0.3a5.dist-info/WHEEL
Junkyard-0.0.3a5.dist-info/top_level.txt
Junkyard-0.0.3a5.dist-info/RECORD
