Metadata-Version: 2.1
Name: Junkyard
Version: 0.0.3a5
Summary: A collection of [certifiable garbage] dev helpers/handlers created by and for the author
Home-page: https://github.com/crushkilldestroy/Junkyard
Author: CKD
Author-email: crushkilldestroy@tuta.io
License: UNKNOWN
Keywords: personal library,not for you,unless you want it
Platform: UNKNOWN
Classifier: Development Status :: 2 - Pre-Alpha
Classifier: Environment :: Console
Classifier: Intended Audience :: Developers
Classifier: Programming Language :: Python :: 3.7
Classifier: License :: OSI Approved :: MIT License
Classifier: Operating System :: OS Independent
Classifier: Topic :: Software Development
Requires-Python: >=3.7
Requires-Dist: colorama
Requires-Dist: wget
